{
    "name": "Venonat",
    "nationalDexNumber": 48,
    "forms": [
        {
            "formName": "venonat",
            "movePool": [
                "headbutt",
                "tackle",
                "take-down",
                "double-edge",
                "supersonic",
                "disable",
                "psybeam",
                "mega-drain",
                "solar-beam",
                "poison-powder",
                "stun-spore",
                "sleep-powder",
                "string-shot",
                "toxic",
                "confusion",
                "psychic",
                "agility",
                "rage",
                "night-shade",
                "mimic",
                "screech",
                "double-team",
                "confuse-ray",
                "reflect",
                "bide",
                "swift",
                "leech-life",
                "flash",
                "psywave",
                "rest",
                "substitute",
                "thief",
                "snore",
                "curse",
                "protect",
                "sludge-bomb",
                "foresight",
                "giga-drain",
                "endure",
                "swagger",
                "attract",
                "sleep-talk",
                "return",
                "frustration",
                "baton-pass",
                "sweet-scent",
                "morning-sun",
                "hidden-power",
                "sunny-day",
                "facade",
                "endeavor",
                "skill-swap",
                "secret-power",
                "poison-fang",
                "signal-beam",
                "natural-gift",
                "toxic-spikes",
                "bug-buzz",
                "energy-ball",
                "zen-headbutt",
                "captivate",
                "bug-bite",
                "venoshock",
                "rage-powder",
                "acid-spray",
                "round",
                "struggle-bug",
                "confide",
                "infestation",
                "lunge",
                "skitter-smack",
                "tera-blast",
                "pounce",
                "psychic-noise"
            ],
            "evolvesInto": [
                "venomoth"
            ],
            "evolvesFrom": "",
            "modes": [
                {
                    "modeName": "venonat",
                    "isDefault": true,
                    "sprite": "https://raw.githubusercontent.com/PokeAPI/sprites/master/sprites/pokemon/48.png",
                    "types": [
                        "bug",
                        "poison"
                    ],
                    "baseStats": {
                        "hp": 60,
                        "attack": 55,
                        "defense": 50,
                        "specialAttack": 40,
                        "specialDefense": 55,
                        "speed": 45
                    },
                    "abilities": [
                        "compound-eyes",
                        "tinted-lens",
                        "run-away"
                    ]
                }
            ]
        }
    ]
}